numexpr/__init__.py
numexpr/bespoke_functions.hpp
numexpr/complex_functions.hpp
numexpr/cpuinfo.py
numexpr/expressions.py
numexpr/functions.hpp
numexpr/interp_body.cpp
numexpr/interpreter.cpp
numexpr/interpreter.cpython-313t-x86_64-linux-musl.so
numexpr/interpreter.hpp
numexpr/interpreter.pyi
numexpr/missing_posix_functions.hpp
numexpr/module.cpp
numexpr/module.hpp
numexpr/msvc_function_stubs.hpp
numexpr/necompiler.py
numexpr/numexpr_config.hpp
numexpr/numexpr_object.cpp
numexpr/numexpr_object.hpp
numexpr/opcodes.hpp
numexpr/py.typed
numexpr/str-two-way.hpp
numexpr/utils.py
numexpr/version.py
numexpr/version.pyi
numexpr/tests/__init__.py
numexpr/tests/conftest.py
numexpr/tests/test_numexpr.py
numexpr/win32/pthread.c
numexpr/win32/pthread.h
numexpr/win32/stdint.h
numexpr.libs/libgcc_s-0cd532bd.so.1
numexpr.libs/libstdc++-5d72f927.so.6.0.33
numexpr-2.14.0.dist-info/METADATA
numexpr-2.14.0.dist-info/WHEEL
numexpr-2.14.0.dist-info/top_level.txt
numexpr-2.14.0.dist-info/RECORD
numexpr-2.14.0.dist-info/licenses/LICENSE.txt
numexpr-2.14.0.dist-info/licenses/LICENSES/cpuinfo.txt
